pytopdrawer/__init__.py
pytopdrawer/pytopdrawer.py
pytopdrawer/read.py
pytopdrawer/topplot.py
pytopdrawer-0.0.9.dist-info/LICENSE
pytopdrawer-0.0.9.dist-info/METADATA
pytopdrawer-0.0.9.dist-info/WHEEL
pytopdrawer-0.0.9.dist-info/entry_points.txt
pytopdrawer-0.0.9.dist-info/RECORD
