Metadata-Version: 2.3
Name: pytopdrawer
Version: 0.0.9
Summary: Plot top files with python and matplotlib (mainly from POWHEG)
License: GPL-3.0-or-later
Author: Alexander Puck Neuwirth
Author-email: alexander@neuwirth-informatik.de
Requires-Python: >=3.8,<4.0
Classifier: License :: OSI Approved :: GNU General Public License v3 or later (GPLv3+)
Classifier: Programming Language :: Python :: 3
Classifier: Programming Language :: Python :: 3.8
Classifier: Programming Language :: Python :: 3.9
Classifier: Programming Language :: Python :: 3.10
Classifier: Programming Language :: Python :: 3.11
Classifier: Programming Language :: Python :: 3.12
Classifier: Programming Language :: Python :: 3.13
Requires-Dist: smpl
Requires-Dist: uncertainties
Project-URL: Repository, https://github.com/APN-Pucky/pytopdrawer
